MYSMALLSITE/__init__.py
MYSMALLSITE/fixer.py
MYSMALLSITE/gener.py
MYSMALLSITE/psite.py
MySmallSite_temp-0.0.2.dist-info/LICENSE
MySmallSite_temp-0.0.2.dist-info/METADATA
MySmallSite_temp-0.0.2.dist-info/WHEEL
MySmallSite_temp-0.0.2.dist-info/top_level.txt
MySmallSite_temp-0.0.2.dist-info/RECORD
