Metadata-Version: 2.1
Name: MySmallSite-temp
Version: 0.0.2
Summary: https://github.com/H-E1P/MySmallSite/pull/1#issuecomment-2594588147
Home-page: https://github.com/c0dk1ddy/MySmallSitePR
Author: c0dk1ddy
Author-email: tax0787bz3@gmail.com
License: UNKNOWN
Keywords: mss tempertal
Platform: UNKNOWN
Classifier: Programming Language :: Python :: 3.6
Classifier: Programming Language :: Python :: 3.7
Classifier: Programming Language :: Python :: 3.8
Classifier: Programming Language :: Python :: 3.9
Classifier: Programming Language :: Python :: 3.10
Classifier: Programming Language :: Python :: 3.11
Classifier: Programming Language :: Python :: 3.12
Requires-Python: >=3.5
License-File: LICENSE
